{"paths":{"0":["Prefabs/rankItem",0],"1":["fishGamePrefabs/bonus",0],"3":["fishGamePrefabs/fish",0],"4":["fishGamePrefabs/net",0],"5":["Prefabs/nextLevelWindow",0],"6":["fishGamePrefabs/bullet",0],"7":["fishGamePrefabs/prize",0]},"types":["cc.Prefab"],"uuids":["05cDnpVRxJJYMzlXX/BEKU","37W5vSkmtNXZPZk9BD7XPr","3aXK0DnatBw5PSIZCskvP3","433XV6ICdAQYrbZPhgXr+o","4dT9q18AlF2bOSfdsx65ic","537fPihRFIgpPJ0V0NXd13","63pST15tVNcKa/L2iJVq40","6b6rXMRpROQpZYYqiCMFi2","71VhFCTINJM6/Ky3oX9nBT","b4P/PCArtIdIH38t6mlw8Y","c1yn80lWlNnbBBvcsWLoGs","d8HsitJHxOYqo801xBk8ev","e8Ueib+qJEhL6mXAHdnwbi","f3d5R3fb9HUZAvmFlzcgFS","01ghw4GPFKH7HA2sjfhWqb","01hX6BRr9FxbMgw455U2CQ","02delMVqdBD70a/HSD99FK","02l6qylIJPxqyH1o1Q1fLx","025SW+e5pLYquZ7hctsryI","033wZRoYlLBaZGKZgaFd7j","04iiGb2gFGhItUqhZTxQKz","046cx5UEtB/6lumSR6YUnC","06bmD5poxO3K6lppNb4wZi","06ktSkDs1F8o462+vaenF+","07LFrgjpJLQqfFNUDczh0q","07VJbCMFRBFrKKajzlbJuC","0agtnZGApKaYPHbRSHUuZU","0eUbmBo9lJzKqcQE4O/tpa","0eYa3o3DRBNrdARyYOvuoe","0eevkMlhNNdqX0sSrFcw7d","12mrHdM1VEy5vs+fJf9SmS","13dF69G19PN7MSPSlDsXkZ","14S6Qjk0JPh6f/ZEU1Op2E","14fUkUcrxJSKAH7voL7tcP","16X3+CC4lL25491rvX4Ml4","17aSSEGbVH74d+BDKfNDBl","17q99X/pFCvZyljv/i8ZZI","189pP6tbFH7alN692J+PvB","19zPV+uR9KCKtTeX31qFDY","1bKoRLHR9OnoMyrpw5S5kO","1bX4TZ2ExGb4d6ZkmcgBaM","1cSx93pWtLjodo/mFMp3lb","1du9KgKbdLDrS5RUX5sSQ1","1d2gLEX+tOZa+4tQf3U2sV","200oZOKElOj5b4hqCS/GtU","2076CBbINMpp678iozggXK","22uI9mEWNGX5qC8dofzR4U","24gKMNEYlBVp3ZDo+SPBVj","242RB5iY1KAJFiX+FMoprp","243QBQRpZEOLbyyhxY11lO","243xT62HhNI6twycU9TaSn","25UBkyE9lDUICSA9QM6x9K","26cCLRK/VFr5pLguGb+6F8","262boPDoNJiqpN5390SZud","265vo/cRhK5r/nq17lUIz1","28ETJTQWtD857G4KgWLaW/","28a/6UH1FBcazzDZWD2ViF","280bu7SUBHD6EC/whpMKOw","29FYIk+N1GYaeWH/q1NxQO","2aBTYQZcFMt7huB3Xs7qYB","2bGACfJnpCZKM739PPwLb9","2bnj2D9JBHi4bx705dSZB9","2dbmQ6omdHoIFU29jxY1Ss","2eTyJsobdIHqCu+IjvPTsb","2e6Of7XlxMmpcUONjD5XjG","33r2k+1xxP3pr+iNyUqfEG","3bfU/pMihClJnjCjkMQiJS","3cMk7zcuFLE5Kxxvrjc6W6","3dFNfFOe9Ab7e2WkfbRhBf","40F2SIjIVBU6jOGukXEM9Z","42dGnJIPdDfJReVy+jKXrP","42u8GKDGhCVobAL7RHln2h","43D4AqKGZA/pGdjKjqblZ2","43yzTC5A5IqJfnLO7rSkLr","45bRuQHEFM2bfvqsRHp9R2","45yTCBCkFPUJEVtu56Z339","46mUtM4zRL25lmWqScY7EO","46/3JLlwRAqKconrbrXKbX","49G4oKTXBJl5bU55gtDhpj","49LBk7l6RC87epam5M7MDp","4aYnCtchVJXoPFXwe5YAmA","4akTIwMc5PnKmraCNddEyD","4b9Mk62ZFJSaSCiB8kHkFB","4dRqWDsr9FYraZ82gMeAv+","4eToG23zhIVJncCmdO8PK1","4fMv+fDktMV6A0ibwEQycx","514sKOrfVOFbL9jIK/fllT","51/dAPXe1DmbVPwhT12Xn2","53OzC4jdBA9YVXUuD9iAQu","54AMJIjYtBGJSPgeLsNnx+","54pgXukWlB+q8585geXx+M","56KDYWgIFLsqjIhXDs/1Om","57LcMsRDRINZiwiPf/pdyQ","59hhuz/1dByaJVuRgsAwR/","59yUDWU4RPKa0YEc2o/EOq","5dbEru8DhK6phXzpcWjtTE","5eHDkTo+dIDqIDag/SdOx+","60DAmKq2JBVLnYZmqrYX0w","61rM3o/eFAK6tYvdKKOULm","642+uqO1tDH6V/3PExUw81","65M/HwnxRNEoKAd5XlLxTp","65b8iMId9NBJjz+9x2QCX7","65crOIQKpEaIvuyGHu4Eol","67QdERciVH6LYJl4IUU2jb","67sDw93E1IW4IExXiU9EnZ","68J8mpdABH+JuRgrQTNHIm","68Ldq34f9BT7iNq8Kz8Rdj","6cqHarN3hM3p/leXUoeBnc","6df3ifJchP7LymrxRyxDRp","6d83LyXLRI2q3OFyiJIiMS","6eKZyVKj1N05Mlsu0BzfMB","70rnvyBFJOb7rjdAzUWJoz","71ZPBJt9ZHjZmPUNcXIypx","71x5mR2LJPJKklxA/omcNn","72pyP5/11MUaSJ35vqGWp0","73Leefq49BX5d4LNJlAVcl","73mDe2GFBCNoYHJsG25RO+","74KHgtChBP04jdl9COx0yN","74SQnaGURP+KbBxTTKcW+o","742l+UiclK0Z010YfbBVFX","77/fGgwGxGIYiQbEKzx+gc","78okD4WpdO4IDN34tRUFVV","79qDbC76FPVZ2D5+Acxfp+","7dl4Spl35PEI2iknxDddgr","7eVL+9q/FLB4SN7Wvl3Thc","7eZ6p/GiVKiaZ7UZiBF66H","7fIQn6mg9BvIn+fsrab/tG","7fvtD5dcVAEoMVDI+CQZw+","80mmw3xphPLLF+sRKAU193","811D0/rqJDKoxNfDcrLoxh","84kZD+xPNAcZ/y8CjszG/R","85OaQzbjdOco7oJRmcmJ8F","86TAbZjk9GmZLgNkGheiB/","86ct3YLtBHp4pnVPm8aU/V","86sbfJ6IFLL4NZ9YN3vnDf","86/kUmlINMhbfJs6TsaW1Y","87dgmLvWpAhoih9LKCfK5u","880/HRUoxG5bMvMQgBqOas","8b4u9163JDJaohriB804zt","8ceE/CUIxMtolOS2VoHu1c","8ch39rXExOv5dRfgGVvL26","92bXCPiSJN+o3sDeEfPzIb","92ksWORcpJOKwXgIj47y0X","94+akd4AtOEKGHrvGouyev","96Ej7m0+1M7YUVheIYBGiE","97fP6bIcdJjrBgVBgAURqL","98MEfGpoBHSJzm85MBUAhh","99E2lhi75MXrVkUFo4ZXoh","9bvaMerUlDyary99mJa6xp","9cQR1uM+pL15wEP2DJiWh8","9druJ0Vk9EAqI9tz8K/39R","9d81grxapFaa4xXfAggWcd","9e0Uv2o35JQrq2dfN/1m46","9fp6uvZg1PGJUtmX/t+pJx","a1JzWLfHdMqYyfbVMYlhB5","a2MjXRFdtLlYQ5ouAFv/+R","a2nu957rJKOKFo0hvTfjmY","a5dSjJ/yFHcJdV8rurTcUp","a52lfF2cJMpbrT1QgDvvYr","a6yZNc7BtCirLMzoOzqYtJ","a7/hRZgLBPzpeaem0YCMli","a8RFdkcwBAkKZ+7hAeknjT","a97XXjjnFG7p2cdcyoH9Xa","ab4U2xySFL6pVgFrbPzLR9","aeQoup3Q1B8JBpMNnnFAf8","af427CtTpASJLcuta8N0wd","b2PuhVQFJNu6cNJq4RBgNw","b5de4VnGpCt7MzUObttYqF","b7HCnN0ShHDLX2p9pCI8A7","b7J97ENiJEELUOUZhHy3jp","b7lO76fZtDkaXxPraw8wQU","b8VfUT+xhH7a4DHOWks54b","b9eo9v7jBAZbmPiOHGW7fE","b9mWKKfqVNQ7ny2KDrNuJZ","ba3V/8BV1B6I6aHIV/Y8JS","bbDelodxdCkqPtznCsgs7D","bdoO8J201CKKxlx7MpcWO8","bdo9lTGVlMX462GcjJXYtF","beD1sMtUFNl4ZLmdT01MNi","c2CjEfyWdBIYX4/vjQe0Yj","c2qWwpaA5LLb7dECEJGabB","c3MNN1XpBKRYVkix6OpDZK","c3MSNipvRCLpakWMLfx/E4","c3f2k4cMpD17YnRo88PZeh","c3rCfPGQJOUqB5FhRKCYj+","c55YVvABVAYIOIobA1Nx+b","c6LilBpM5HlK3dgBciRL//","c7wfAoPeVLl5XqS+ez3YEz","c8ge8raZRGi4lmOyoXwUOf","c8k5wyimxOYbSxA5A7fEGJ","c94maO84RNnp8AmndvMF6T","ccqdEj32FHcLMrNWMS7Ka+","cdDG1YyiZLXogoBdt4/6eQ","ceFdi3rOhLbq+Wa6IH/LZG","ce8NMlwtFJS5jdYSIoih2j","cfjRaSM1NE37gk9s8Q+Lah","d2w6aHpjZKConf07fllV9b","d3qI6Sf31P7qxCIFhe/A76","d4ZXailUZEeYjZFdIx5jA+","d4+ncOutdFeZizWGv8t31j","d5l9OK0gBKPY0ytVeanMjo","d9MvSAxKhJ1ozaoDFD5REV","da7QSw+URNbbJZ5aMUAm+p","dfXNS0Q6FLNrNh6grb9xnC","dfZMY581VIPZCBxpeoXQP+","dfvHY1tgFLy4J0FdyPnZLj","e0hO6IviBNhrqzQkQetz/e","e3YoXl5eRBtLc5dwwQ/hXJ","e3na3gx6hKJ5V4rX+WX7fH","e4rYBKqutEebNpOprib2+A","e8Y0KMqYNIx7DQRhkgxRS3","e8uTMTLVZAGr9P1wwSgEE7","e82lCFLhNBZo9wUD4VPLWU","e97GVMl6JHh5Ml5qEDdSGa","eazagGOaBL6b0sx4qKzxfd","ea+Vw2J/ZN0Y04jv7JF37S","ecpdLyjvZBwrvm+cedCcQy","edeWjhcLFB+J8nzKHGEYlg","ed3XUOF6dDnoyP77Cp1hC4","efTomVxn1Of6jUJpsYku1+","efxttoD/1OhoMnY/888Idb","f0BIwQ8D5Ml7nTNQbh1YlS","f0eL0To1ZMxJKRHf2QkO7K","f3TuO+xtFL94xrT5qYGAjR","f59gVXXedO3Ku4kize3ogJ","f61WLjAi5BHIMGeSDRdAYR","f7cJSdiMdDvZ3yRKjDMDdc","f8B32GXeBNpLgCW083cgnT","faQLedj39KcKwez6nqdnlv","fasvNoGfxOibwGhV/SOZHx","fedSix6ZNNWLc4oVVJIt5e","ff4zNj7gFOQb3QOISebVb2"],"scenes":{},"redirect":[16,0,216,0],"deps":["internal"],"packs":{"018519ec5":[22,23,26,30,33,46,3,75,127,136,141,143,149,158,173,177,187,188,192,200,207,217,227],"04bf3a6f3":[84,117,123,133,157,186,223],"07c3cef89":[0,148],"098bf2623":[14,15,17,19,20,21,24,25,27,28,29,31,32,35,36,37,39,40,41,42,44,45,47,48,49,50,51,52,53,54,55,56,57,59,60,62,63,64,65,66,67,69,70,71,72,73,74,76,78,81,82,83,85,86,87,88,89,90,91,92,93,94,95,96,98,99,100,101,102,103,104,105,106,108,109,110,111,112,114,115,116,118,119,120,122,124,125,126,128,129,130,131,134,135,139,140,142,144,146,147,150,151,152,153,154,156,159,160,161,162,163,164,165,166,167,168,169,170,171,172,174,175,176,179,180,182,183,184,185,189,190,191,193,194,195,196,197,198,199,201,202,203,205,206,208,209,210,211,212,214,215,219,220,222,224,225,226,228,229,230,231],"0a08e857e":[34,68,4,107,121,181,204,218],"0efcd58f0":[79,145],"0f644ff1b":[58,5,155,213,221],"0f6d98730":[2,8,9,10,11,12,13],"0fcd234a6":[18,38,43,61,1,77,80,97,113,132,137,138,178]},"name":"resources","importBase":"import","nativeBase":"native","debug":false,"isZip":false,"encrypted":false,"versions":{"import":["018519ec5","f819b","04bf3a6f3","fe356","07c3cef89","4999d","098bf2623","1c25f","0a08e857e","3e869","0efcd58f0","b81ac","0f644ff1b","db5ae","0f6d98730","a5a37","0fcd234a6","32000",6,"050a9",7,"e6f6a"],"native":[2,"56ff3",8,"c06a9",9,"83fcc",10,"2a421",11,"cdbc9",12,"90cf4",13,"c1880"]}}